{
  "0hmX": {
    "reviewsReceived": 4,
    "rejectionsReceived": 0,
    "approvalsReceived": 2,
    "approvalsGiven": 2,
    "rejectionsGiven": 0,
    "prsOpened": 6,
    "prsMerged": 5,
    "issuesCreated": 0,
    "bountiedIssuesCount": 0,
    "bountiedIssuesTotal": 0,
    "distinctPrsReviewedNonCodeOwner": 2,
    "discussionComments": 0,
    "discussionNormalComments": 0,
    "discussionGreatInformativeComments": 0,
    "discussionIncredibleComments": 0,
    "distinctPrsReviewedAsCodeOwner": 0,
    "score": 10,
    "stars": "⭐",
    "major": 1,
    "minor": 1,
    "tiny": 3
  },
  "Abse2001": {
    "reviewsReceived": 4,
    "rejectionsReceived": 0,
    "approvalsReceived": 4,
    "approvalsGiven": 5,
    "rejectionsGiven": 0,
    "prsOpened": 5,
    "prsMerged": 4,
    "issuesCreated": 0,
    "bountiedIssuesCount": 0,
    "bountiedIssuesTotal": 0,
    "distinctPrsReviewedNonCodeOwner": 2,
    "discussionComments": 0,
    "discussionNormalComments": 0,
    "discussionGreatInformativeComments": 0,
    "discussionIncredibleComments": 0,
    "reposOwned": [
      {
        "repo": "tscircuit/pcb-viewer",
        "paths": [
          "*"
        ]
      },
      {
        "repo": "tscircuit/3d-viewer",
        "paths": [
          "*"
        ]
      },
      {
        "repo": "tscircuit/circuit-to-canvas",
        "paths": [
          "*"
        ]
      }
    ],
    "distinctPrsReviewedAsCodeOwner": 2,
    "score": 11,
    "stars": "⭐⭐",
    "major": 0,
    "minor": 3,
    "tiny": 1
  },
  "AnasSarkiz": {
    "reviewsReceived": 2,
    "rejectionsReceived": 0,
    "approvalsReceived": 2,
    "approvalsGiven": 0,
    "rejectionsGiven": 0,
    "prsOpened": 2,
    "prsMerged": 2,
    "issuesCreated": 0,
    "bountiedIssuesCount": 0,
    "bountiedIssuesTotal": 0,
    "distinctPrsReviewedNonCodeOwner": 0,
    "discussionComments": 0,
    "discussionNormalComments": 0,
    "discussionGreatInformativeComments": 0,
    "discussionIncredibleComments": 0,
    "score": 4,
    "stars": "⭐",
    "major": 0,
    "minor": 2,
    "tiny": 0
  },
  "ArnavK-09": {
    "reviewsReceived": 8,
    "rejectionsReceived": 0,
    "approvalsReceived": 5,
    "approvalsGiven": 1,
    "rejectionsGiven": 0,
    "prsOpened": 8,
    "prsMerged": 8,
    "issuesCreated": 0,
    "bountiedIssuesCount": 0,
    "bountiedIssuesTotal": 0,
    "distinctPrsReviewedNonCodeOwner": 0,
    "discussionComments": 0,
    "discussionNormalComments": 0,
    "discussionGreatInformativeComments": 0,
    "discussionIncredibleComments": 0,
    "distinctPrsReviewedAsCodeOwner": 0,
    "score": 20,
    "stars": "⭐⭐",
    "major": 3,
    "minor": 3,
    "tiny": 2
  },
  "Devesh36": {
    "reviewsReceived": 0,
    "rejectionsReceived": 0,
    "approvalsReceived": 0,
    "approvalsGiven": 1,
    "rejectionsGiven": 0,
    "prsOpened": 0,
    "prsMerged": 0,
    "issuesCreated": 0,
    "bountiedIssuesCount": 0,
    "bountiedIssuesTotal": 0,
    "distinctPrsReviewedNonCodeOwner": 1,
    "distinctPrsReviewedAsCodeOwner": 0,
    "score": 0,
    "stars": ""
  },
  "Heinrich-XIAO": {
    "reviewsReceived": 9,
    "rejectionsReceived": 1,
    "approvalsReceived": 5,
    "approvalsGiven": 0,
    "rejectionsGiven": 0,
    "prsOpened": 4,
    "prsMerged": 2,
    "issuesCreated": 0,
    "bountiedIssuesCount": 0,
    "bountiedIssuesTotal": 0,
    "distinctPrsReviewedNonCodeOwner": 0,
    "discussionComments": 0,
    "discussionNormalComments": 0,
    "discussionGreatInformativeComments": 0,
    "discussionIncredibleComments": 0,
    "distinctPrsReviewedAsCodeOwner": 0,
    "score": 2,
    "stars": "",
    "major": 0,
    "minor": 0,
    "tiny": 2
  },
  "MustafaMulla29": {
    "reviewsReceived": 15,
    "rejectionsReceived": 2,
    "approvalsReceived": 10,
    "approvalsGiven": 0,
    "rejectionsGiven": 1,
    "prsOpened": 15,
    "prsMerged": 11,
    "issuesCreated": 0,
    "bountiedIssuesCount": 0,
    "bountiedIssuesTotal": 0,
    "distinctPrsReviewedNonCodeOwner": 0,
    "discussionComments": 0,
    "discussionNormalComments": 0,
    "discussionGreatInformativeComments": 0,
    "discussionIncredibleComments": 0,
    "distinctPrsReviewedAsCodeOwner": 0,
    "score": 20,
    "stars": "⭐⭐",
    "major": 2,
    "minor": 3,
    "tiny": 6
  },
  "Rhan2020": {
    "reviewsReceived": 0,
    "rejectionsReceived": 0,
    "approvalsReceived": 0,
    "approvalsGiven": 0,
    "rejectionsGiven": 0,
    "prsOpened": 1,
    "prsMerged": 0,
    "issuesCreated": 0,
    "bountiedIssuesCount": 0,
    "bountiedIssuesTotal": 0,
    "distinctPrsReviewedNonCodeOwner": 0,
    "discussionComments": 0,
    "discussionNormalComments": 0,
    "discussionGreatInformativeComments": 0,
    "discussionIncredibleComments": 0,
    "score": 0,
    "stars": ""
  },
  "ShiboSoftwareDev": {
    "reviewsReceived": 7,
    "rejectionsReceived": 0,
    "approvalsReceived": 7,
    "approvalsGiven": 5,
    "rejectionsGiven": 0,
    "prsOpened": 7,
    "prsMerged": 7,
    "issuesCreated": 0,
    "bountiedIssuesCount": 0,
    "bountiedIssuesTotal": 0,
    "distinctPrsReviewedNonCodeOwner": 1,
    "distinctPrsReviewedAsCodeOwner": 4,
    "reposOwned": [
      {
        "repo": "tscircuit/circuit-json-to-gerber",
        "paths": [
          "*"
        ]
      }
    ],
    "score": 19,
    "stars": "⭐⭐",
    "major": 1,
    "minor": 4,
    "tiny": 2
  },
  "agent-steven": {
    "reviewsReceived": 1,
    "rejectionsReceived": 1,
    "approvalsReceived": 0,
    "approvalsGiven": 0,
    "rejectionsGiven": 0,
    "prsOpened": 1,
    "prsMerged": 0,
    "issuesCreated": 0,
    "bountiedIssuesCount": 0,
    "bountiedIssuesTotal": 0,
    "distinctPrsReviewedNonCodeOwner": 0,
    "discussionComments": 0,
    "discussionNormalComments": 0,
    "discussionGreatInformativeComments": 0,
    "discussionIncredibleComments": 0,
    "score": 0,
    "stars": ""
  },
  "bamontejano": {
    "reviewsReceived": 0,
    "rejectionsReceived": 0,
    "approvalsReceived": 0,
    "approvalsGiven": 0,
    "rejectionsGiven": 0,
    "prsOpened": 2,
    "prsMerged": 0,
    "issuesCreated": 0,
    "bountiedIssuesCount": 0,
    "bountiedIssuesTotal": 0,
    "distinctPrsReviewedNonCodeOwner": 0,
    "discussionComments": 0,
    "discussionNormalComments": 0,
    "discussionGreatInformativeComments": 0,
    "discussionIncredibleComments": 0,
    "score": 0,
    "stars": ""
  },
  "buildingvibes": {
    "reviewsReceived": 12,
    "rejectionsReceived": 1,
    "approvalsReceived": 0,
    "approvalsGiven": 0,
    "rejectionsGiven": 0,
    "prsOpened": 25,
    "prsMerged": 0,
    "issuesCreated": 0,
    "bountiedIssuesCount": 0,
    "bountiedIssuesTotal": 0,
    "distinctPrsReviewedNonCodeOwner": 0,
    "discussionComments": 0,
    "discussionNormalComments": 0,
    "discussionGreatInformativeComments": 0,
    "discussionIncredibleComments": 0,
    "distinctPrsReviewedAsCodeOwner": 0,
    "score": 0,
    "stars": ""
  },
  "imrishabh18": {
    "reviewsReceived": 4,
    "rejectionsReceived": 0,
    "approvalsReceived": 1,
    "approvalsGiven": 3,
    "rejectionsGiven": 0,
    "prsOpened": 12,
    "prsMerged": 11,
    "issuesCreated": 0,
    "bountiedIssuesCount": 0,
    "bountiedIssuesTotal": 0,
    "distinctPrsReviewedNonCodeOwner": 1,
    "distinctPrsReviewedAsCodeOwner": 0,
    "reposOwned": [
      {
        "repo": "tscircuit/tscircuit.com",
        "paths": [
          "*"
        ]
      }
    ],
    "score": 23,
    "stars": "⭐⭐",
    "major": 2,
    "minor": 5,
    "tiny": 4
  },
  "nailoo": {
    "reviewsReceived": 8,
    "rejectionsReceived": 1,
    "approvalsReceived": 5,
    "approvalsGiven": 1,
    "rejectionsGiven": 1,
    "prsOpened": 6,
    "prsMerged": 4,
    "issuesCreated": 0,
    "bountiedIssuesCount": 0,
    "bountiedIssuesTotal": 0,
    "distinctPrsReviewedNonCodeOwner": 1,
    "discussionComments": 0,
    "discussionNormalComments": 0,
    "discussionGreatInformativeComments": 0,
    "discussionIncredibleComments": 0,
    "distinctPrsReviewedAsCodeOwner": 0,
    "score": 6,
    "stars": "⭐",
    "major": 0,
    "minor": 1,
    "tiny": 3
  },
  "rushabhcodes": {
    "reviewsReceived": 27,
    "rejectionsReceived": 5,
    "approvalsReceived": 7,
    "approvalsGiven": 1,
    "rejectionsGiven": 0,
    "prsOpened": 8,
    "prsMerged": 3,
    "issuesCreated": 0,
    "bountiedIssuesCount": 0,
    "bountiedIssuesTotal": 0,
    "distinctPrsReviewedNonCodeOwner": 0,
    "discussionComments": 0,
    "discussionNormalComments": 0,
    "discussionGreatInformativeComments": 0,
    "discussionIncredibleComments": 0,
    "distinctPrsReviewedAsCodeOwner": 0,
    "score": 7,
    "stars": "⭐",
    "major": 1,
    "minor": 1,
    "tiny": 1
  },
  "seveibar": {
    "reviewsReceived": 7,
    "rejectionsReceived": 0,
    "approvalsReceived": 0,
    "approvalsGiven": 32,
    "rejectionsGiven": 10,
    "prsOpened": 23,
    "prsMerged": 21,
    "issuesCreated": 0,
    "bountiedIssuesCount": 0,
    "bountiedIssuesTotal": 0,
    "distinctPrsReviewedNonCodeOwner": 21,
    "discussionComments": 0,
    "discussionNormalComments": 0,
    "discussionGreatInformativeComments": 0,
    "discussionIncredibleComments": 0,
    "distinctPrsReviewedAsCodeOwner": 10,
    "reposOwned": [
      {
        "repo": "tscircuit/footprinter",
        "paths": [
          "*"
        ]
      },
      {
        "repo": "tscircuit/tscircuit.com",
        "paths": [
          "*"
        ]
      }
    ],
    "score": 39,
    "stars": "⭐⭐⭐",
    "major": 2,
    "minor": 11,
    "tiny": 8
  },
  "shehaban": {
    "reviewsReceived": 6,
    "rejectionsReceived": 2,
    "approvalsReceived": 2,
    "approvalsGiven": 0,
    "rejectionsGiven": 0,
    "prsOpened": 3,
    "prsMerged": 1,
    "issuesCreated": 0,
    "bountiedIssuesCount": 0,
    "bountiedIssuesTotal": 0,
    "distinctPrsReviewedNonCodeOwner": 0,
    "discussionComments": 0,
    "discussionNormalComments": 0,
    "discussionGreatInformativeComments": 0,
    "discussionIncredibleComments": 0,
    "score": 2,
    "stars": "",
    "major": 0,
    "minor": 1,
    "tiny": 0
  },
  "techmannih": {
    "reviewsReceived": 8,
    "rejectionsReceived": 0,
    "approvalsReceived": 3,
    "approvalsGiven": 2,
    "rejectionsGiven": 2,
    "prsOpened": 8,
    "prsMerged": 3,
    "issuesCreated": 0,
    "bountiedIssuesCount": 0,
    "bountiedIssuesTotal": 0,
    "distinctPrsReviewedNonCodeOwner": 1,
    "distinctPrsReviewedAsCodeOwner": 1,
    "reposOwned": [
      {
        "repo": "tscircuit/circuit-to-canvas",
        "paths": [
          "*"
        ]
      }
    ],
    "score": 11,
    "stars": "⭐⭐",
    "major": 2,
    "minor": 0,
    "tiny": 1
  },
  "tscircuitbot": {
    "reviewsReceived": 0,
    "rejectionsReceived": 0,
    "approvalsReceived": 0,
    "approvalsGiven": 0,
    "rejectionsGiven": 0,
    "prsOpened": 229,
    "prsMerged": 207,
    "issuesCreated": 0,
    "bountiedIssuesCount": 0,
    "bountiedIssuesTotal": 0,
    "distinctPrsReviewedNonCodeOwner": 0,
    "discussionComments": 0,
    "discussionNormalComments": 0,
    "discussionGreatInformativeComments": 0,
    "discussionIncredibleComments": 0,
    "score": 13.5,
    "stars": "⭐⭐",
    "major": 0,
    "minor": 0,
    "tiny": 207
  },
  "xiuqiang1995": {
    "reviewsReceived": 1,
    "rejectionsReceived": 1,
    "approvalsReceived": 0,
    "approvalsGiven": 0,
    "rejectionsGiven": 0,
    "prsOpened": 1,
    "prsMerged": 0,
    "issuesCreated": 0,
    "bountiedIssuesCount": 0,
    "bountiedIssuesTotal": 0,
    "distinctPrsReviewedNonCodeOwner": 0,
    "discussionComments": 0,
    "discussionNormalComments": 0,
    "discussionGreatInformativeComments": 0,
    "discussionIncredibleComments": 0,
    "score": 0,
    "stars": ""
  }
}